MANIFEST.in
README.md
redis-py_license
setup.py
ledis/__init__.py
ledis/_compat.py
ledis/client.py
ledis/connection.py
ledis/exceptions.py
ledis/utils.py
ledis.egg-info/PKG-INFO
ledis.egg-info/SOURCES.txt
ledis.egg-info/dependency_links.txt
ledis.egg-info/top_level.txt
tests/__init__.py
tests/test_cmd_hash.py
tests/test_cmd_kv.py
tests/test_cmd_list.py
tests/test_cmd_zset.py
tests/test_others.py