Metadata-Version: 1.1
Name: ledis
Version: 0.0.1
Summary: Python client for ledisdb key-value database
Home-page: https://github.com/siddontang/ledisdb
Author: UNKNOWN
Author-email: UNKNOWN
License: MIT
Keywords: ledis,key-value store
Platform: UNKNOWN
Classifier: Development Status :: 5 - Production/Stable
Classifier: Environment :: Console
Classifier: Intended Audience :: Developers
Classifier: License :: OSI Approved :: MIT License
Classifier: Operating System :: OS Independent
Classifier: Programming Language :: Python
Classifier: Programming Language :: Python :: 2.6
Classifier: Programming Language :: Python :: 2.7
